{
  "returnCode": "SUC0000",
  "errorMsg": null,
  "body": {
    "docId": null,
    "docKey": "4872420241212213000458",
    "docName": "导入预算科目信息",
    "docType": "application/octet-stream",
    "bucketName": "lw36.01-public-prd",
    "parentMenuId": null,
    "parentMenuName": null,
    "menuId": null,
    "docVersion": "1.0",
    "docStatus": "1",
    "docCnt": "##接口调用地址 \n 生产环境地址：https://api.cmbchina.com/itrip/xft-api/v1/budget/import/subject \n 测试环境地址：https://api.cmburl.cn:8065/itrip/xft-api/uat/v1/budget/import/subject \n ## 接口描述 \n支持外部系统通过接口导入预算科目信息进入费控，不支持部分成功 \n## 调用方式 \n METHOD: POST  \n CONTENT-TYPE: application/json \n## 接口输入参数 \n <restparamstable>[{\"elementData\":{\"name\":\"root\",\"type\":\"OBJECT\",\"desc\":\"请求头根节点\",\"label\":\"虚拟根节点\"}}]</restparamstable><restparamstable>[{\"elementData\":{\"name\":\"root\",\"type\":\"OBJECT\",\"desc\":\"请求体根节点\",\"label\":\"虚拟根节点\"},\"children\":[{\"elementData\":{\"type\":\"STRING\",\"name\":\"opsEmpNumber\",\"required\":true,\"label\":\"%E6%93%8D%E4%BD%9C%E4%BA%BA%09\",\"exampleValue\":\"001\",\"desc\":\"%20%E5%A1%AB%E5%86%99%E5%91%98%E5%B7%A5%E8%8A%B1%E5%90%8D%E5%86%8C%E7%BC%96%E7%A0%81%0D%0A%0D%0A%0D%0A\"}},{\"elementData\":{\"type\":\"ARRAY\",\"name\":\"subjectTypes\",\"required\":false,\"label\":\"%E5%AF%BC%E5%85%A5%E9%A2%84%E7%AE%97%E7%A7%91%E7%9B%AE%E5%88%86%E7%B1%BB%E5%88%97%E8%A1%A8\",\"exampleValue\":\"\",\"desc\":\"%20%E4%BC%A0%E5%85%A5%E5%88%99%E8%BF%9B%E8%A1%8C%E5%AF%BC%E5%85%A5%E9%A2%84%E7%AE%97%E7%A7%91%E7%9B%AE%E5%88%86%E7%B1%BB%0A%E6%9C%80%E5%A4%9A%E6%94%AF%E6%8C%81%E4%BC%A0%E5%85%A5100%E6%9D%A1\",\"maxLength\":\"100\"},\"children\":[{\"elementData\":{\"type\":\"STRING\",\"name\":\"budgetSubTypeId\",\"required\":true,\"label\":\"%E9%A2%84%E7%AE%97%E7%A7%91%E7%9B%AE%E5%88%86%E7%B1%BBID\",\"exampleValue\":\"z001\",\"desc\":\"%20%E4%BB%85%E6%94%AF%E6%8C%81%E6%95%B0%E5%AD%97%E5%92%8C%E5%AD%97%E6%AF%8D\",\"maxLength\":\"50\"}},{\"elementData\":{\"type\":\"STRING\",\"name\":\"budgetSubTypeName\",\"required\":true,\"label\":\"%E9%A2%84%E7%AE%97%E7%A7%91%E7%9B%AE%E5%88%86%E7%B1%BB%E5%90%8D%E7%A7%B0\",\"exampleValue\":\"api%E5%AF%BC%E5%85%A5%E7%A7%91%E7%9B%AE%E5%88%86%E7%B1%BB\",\"desc\":\"%20%E9%A2%84%E7%AE%97%E7%A7%91%E7%9B%AE%E5%88%86%E7%B1%BB%E5%90%8D%E7%A7%B0\",\"maxLength\":\"150\"}}]},{\"elementData\":{\"type\":\"ARRAY\",\"name\":\"subjects\",\"required\":true,\"label\":\"%E5%AF%BC%E5%85%A5%E9%A2%84%E7%AE%97%E7%A7%91%E7%9B%AE%E5%88%97%E8%A1%A8\",\"exampleValue\":\"\",\"desc\":\"%20%E6%9C%80%E5%A4%9A%E6%94%AF%E6%8C%81%E4%BC%A0%E5%85%A5100%E6%9D%A1\",\"maxLength\":\"100\"},\"children\":[{\"elementData\":{\"type\":\"STRING\",\"name\":\"expIds\",\"required\":true,\"label\":\"%E9%A2%84%E7%AE%97%E7%A7%91%E7%9B%AE%E5%85%B3%E8%81%94%E8%B4%B9%E7%94%A8%E7%B1%BB%E5%9E%8Bid%E5%88%97%E8%A1%A8\",\"exampleValue\":\"01%2C02\",\"desc\":\"%20%E5%A1%AB%E5%86%99%E8%B4%B9%E7%94%A8%E7%B1%BB%E5%9E%8B%E7%BC%96%E7%A0%81%EF%BC%8C%E4%BB%A5%E8%8B%B1%E6%96%87%E9%80%97%E5%8F%B7%2C%E5%88%86%E5%89%B2\"}},{\"elementData\":{\"type\":\"STRING\",\"name\":\"subName\",\"required\":true,\"label\":\"%E9%A2%84%E7%AE%97%E7%A7%91%E7%9B%AE%E5%90%8D%E7%A7%B0\",\"exampleValue\":\"api%E6%B5%8B%E8%AF%95%E7%A7%91%E7%9B%AE%E5%90%8D%E7%A7%B01-1\",\"desc\":\"%20%E9%A2%84%E7%AE%97%E7%A7%91%E7%9B%AE%E5%90%8D%E7%A7%B0\",\"maxLength\":\"100\"}},{\"elementData\":{\"type\":\"STRING\",\"name\":\"subTypeId\",\"required\":true,\"label\":\"%E9%A2%84%E7%AE%97%E7%A7%91%E7%9B%AE%E6%89%80%E5%B1%9E%E5%88%86%E7%B1%BBID\",\"exampleValue\":\"z001\",\"desc\":\"%20%E4%BB%85%E6%94%AF%E6%8C%81%E6%95%B0%E5%AD%97%E5%92%8C%E5%AD%97%E6%AF%8D\",\"maxLength\":\"50\"}}]}]}]</restparamstable><restparamstable>[{\"elementData\":{\"name\":\"root\",\"type\":\"OBJECT\",\"desc\":\"query根节点\",\"label\":\"虚拟根节点\"}}]</restparamstable> \n## 接口输出参数\n <restparamstable>[{\"elementData\":{\"name\":\"root\",\"type\":\"OBJECT\",\"desc\":\"响应头根节点\",\"label\":\"虚拟根节点\"}}]</restparamstable><restparamstable>[{\"elementData\":{\"name\":\"root\",\"type\":\"OBJECT\",\"desc\":\"响应体根节点\",\"label\":\"虚拟根节点\"},\"children\":[{\"elementData\":{\"type\":\"OBJECT\",\"name\":\"data\",\"required\":false,\"label\":\"%E6%8E%A5%E5%8F%A3%E8%BF%94%E5%9B%9E%E5%AF%BC%E5%85%A5%E7%BB%93%E6%9E%9C%09\",\"exampleValue\":\"\",\"desc\":\"\"},\"children\":[{\"elementData\":{\"type\":\"BOOLEAN\",\"name\":\"success\",\"required\":false,\"label\":\"%E5%AF%BC%E5%85%A5%E6%98%AF%E5%90%A6%E6%88%90%E5%8A%9F%E7%8A%B6%E6%80%81%09\",\"exampleValue\":\"false\",\"desc\":\"%20true%E8%AF%B4%E6%98%8E%E5%AF%BC%E5%85%A5%E6%88%90%E5%8A%9F%0D%0Afalse%E8%AF%B4%E6%98%8E%E5%AF%BC%E5%85%A5%E5%A4%B1%E8%B4%A5\"}},{\"elementData\":{\"type\":\"ARRAY\",\"name\":\"errors\",\"required\":false,\"label\":\"%E5%AF%BC%E5%85%A5%E5%A4%B1%E8%B4%A5%E5%8E%9F%E5%9B%A0%E5%88%97%E8%A1%A8\",\"exampleValue\":\"\",\"desc\":\"%20%E5%A6%82%E6%9E%9C%E5%AF%BC%E5%85%A5%E5%A4%B1%E8%B4%A5%EF%BC%8C%E8%BF%99%E9%87%8C%E4%BC%9A%E8%BF%94%E5%9B%9E%E5%85%B7%E4%BD%93%E7%9A%84%E5%AF%BC%E5%85%A5%E5%A4%B1%E8%B4%A5%E5%8E%9F%E5%9B%A0%0D%0A%E5%A6%82%E6%9E%9C%E6%98%AF%E5%AF%BC%E5%85%A5%E6%88%90%E5%8A%9F%EF%BC%8C%E5%88%99%E4%B8%BA%E8%BF%99%E9%87%8C%E4%B8%BA%E7%A9%BA\"},\"children\":[{\"elementData\":{\"type\":\"STRING\",\"name\":\"type\",\"required\":false,\"label\":\"%E5%AF%BC%E5%85%A5%E5%A4%B1%E8%B4%A5%E7%9A%84%E5%8E%9F%E5%9B%A0%E7%B1%BB%E5%9E%8B\",\"exampleValue\":\"%E9%A2%84%E7%AE%97%E7%A7%91%E7%9B%AE%E5%88%86%E7%B1%BB%E7%BC%96%E7%A0%81\",\"desc\":\"%20%E9%A2%84%E7%AE%97%E7%A7%91%E7%9B%AE%E5%88%86%E7%B1%BB%E7%BC%96%E7%A0%81%0A%E9%A2%84%E7%AE%97%E7%A7%91%E7%9B%AE%E5%88%86%E7%B1%BB%E5%90%8D%E7%A7%B0%0A%E9%A2%84%E7%AE%97%E7%A7%91%E7%9B%AE%E5%90%8D%E7%A7%B0%0A%E5%85%81%E8%AE%B8%E5%8D%A0%E7%94%A8%E7%9A%84%E8%B4%B9%E7%94%A8%2F%E8%A1%A5%E8%B4%B4%E7%B1%BB%E5%9E%8B\"}},{\"elementData\":{\"type\":\"LONG\",\"name\":\"index\",\"required\":false,\"label\":\"%E5%AF%BC%E5%85%A5%E5%A4%B1%E8%B4%A5%E7%9A%84%E7%A7%91%E7%9B%AE%E5%BA%8F%E5%8F%B7\",\"exampleValue\":\"1\",\"desc\":\"\"}},{\"elementData\":{\"type\":\"ARRAY\",\"name\":\"msg\",\"required\":false,\"label\":\"%E5%AF%BC%E5%85%A5%E5%A4%B1%E8%B4%A5%E7%9A%84%E5%8E%9F%E5%9B%A0%E5%88%97%E8%A1%A8\",\"exampleValue\":\"%5B%22%E9%A2%84%E7%AE%97%E7%A7%91%E7%9B%AE%E5%88%86%E7%B1%BB%E5%90%8D%E7%A7%B0%E3%80%90api%E5%AF%BC%E5%85%A5%E7%A7%91%E7%9B%AE%E5%88%86%E7%B1%BB1%E3%80%91%E5%B7%B2%E5%AD%98%E5%9C%A8%22%2C%22%E9%A2%84%E7%AE%97%E7%A7%91%E7%9B%AE%E5%88%86%E7%B1%BB%E5%90%8D%E7%A7%B0%E3%80%90api%E5%AF%BC%E5%85%A5%E7%A7%91%E7%9B%AE%E5%88%86%E7%B1%BB1%E3%80%91%E6%9C%89%E9%87%8D%E5%A4%8D%E9%A1%B9%22%5D\",\"desc\":\"%20%E5%AF%BC%E5%85%A5%E5%A4%B1%E8%B4%A5%E5%8E%9F%E5%9B%A0%E5%88%97%E8%A1%A8%EF%BC%8C%E5%85%83%E7%B4%A0%E4%B8%BA%E5%85%B7%E4%BD%93%E5%A4%B1%E8%B4%A5%E5%8E%9F%E5%9B%A0%E5%AD%97%E7%AC%A6%E4%B8%B2\"},\"children\":[],\"open\":false}]}]},{\"elementData\":{\"type\":\"BOOLEAN\",\"name\":\"success\",\"required\":false,\"label\":\"%E6%8E%A5%E5%8F%A3%E8%B0%83%E7%94%A8%E6%88%90%E5%8A%9F%E7%8A%B6%E6%80%81%09\",\"exampleValue\":\"true\",\"desc\":\"%20true%E8%AF%B4%E6%98%8E%E6%8E%A5%E5%8F%A3%E8%B0%83%E7%94%A8%E6%88%90%E5%8A%9F%0D%0Afalse%E8%AF%B4%E6%98%8E%E6%8E%A5%E5%8F%A3%E8%B0%83%E7%94%A8%E5%A4%B1%E8%B4%A5\"}},{\"elementData\":{\"type\":\"STRING\",\"name\":\"message\",\"required\":false,\"label\":\"%E6%8E%A5%E5%8F%A3%E8%B0%83%E7%94%A8%E8%BF%94%E5%9B%9E%E4%BF%A1%E6%81%AF%09\",\"exampleValue\":\"%E8%B0%83%E7%94%A8%E6%88%90%E5%8A%9F%EF%BC%81\",\"desc\":\"\"}}]}]</restparamstable> \n## 接口调用示例 \n #### 请求报文\n```json\n{\n  \"opsEmpNumber\": \"2\",\n  \"subjectTypes\": [\n    {\n      \"budgetSubTypeId\": \"z001\",\n      \"budgetSubTypeName\": \"api导入科目分类1\"\n    }\n  ],\n  \"subjects\": [\n    {\n      \"expIds\": \"01,02\",\n      \"subName\": \"api测试科目名称1-1\",\n      \"subTypeId\": \"z001\"\n    }\n  ]\n}\n```\n#### 响应报文\n#### 接口调用失败的报文，示例仅为其中一部分失败样例\n```json\n{\n    \"success\": false,\n    \"message\": \"导入的预算科目分类和预算科目为空\"\n}\n```\n#### 导入成功的报文\n```json\n{\n    \"data\": {\n        \"success\": true,\n        \"errors\": []\n    },\n    \"success\": true,\n    \"message\": \"调用成功！\"\n}\n```\n#### 导入失败的报文，示例仅为其中一部分失败样例\n```json\n{\n    \"data\": {\n        \"success\": false,\n        \"errors\": [\n            {\n                \"type\": \"预算科目分类编码\",\n                \"index\": 1,\n                \"msg\": [\n                    \"预算科目分类编码【z001】已存在\"\n                ]\n            }\n        ]\n    },\n    \"success\": true,\n    \"message\": \"调用成功！\"\n}\n```  \n## 错误码说明 \n外层success为接口调用状态 true为成功 其余都是失败\ndata内的sucess为实际导入成功状态， true为成功 其余都是失败\n\n常见报错如下：\n对于导入的预算科目分类列表：\n预算科目分类编码【xx】已存在\n预算科目分类编码【xx】有重复项\n预算科目分类名称【xx】已存在\n预算科目分类名称【xx】有重复项\n预算科目分类名称不能为空\n预算科目未配置费用或补助\n\n对于导入的预算科目列表：\n允许占用的费用/补贴类型【xx】不存在\n同一个科目不允许存在相同的费用/补贴类型\n预算科目名称【xx】已存在\n预算科目名称【xx】有重复项\n预算科目名称不能为空\n科目所属分类【xx】不存在",
    "docCntHtml": "<h2>接口调用地址</h2><p>生产环境地址：https://api.cmbchina.com/itrip/xft-api/v1/budget/import/subject</p><p>测试环境地址：https://api.cmburl.cn:8065/itrip/xft-api/uat/v1/budget/import/subject</p> <h2>接口描述</h2><p><p>支持外部系统通过接口导入预算科目信息进入费控，不支持部分成功</p>\n</p> <h2>调用方式</h2><p>METHOD: POST</p><p>CONTENT-TYPE: APPLICATION/JSON</p> <h2>接口输入参数</h2>{\"requestHeader\":[{\"elementData\":{\"name\":\"root\",\"type\":\"OBJECT\",\"desc\":\"请求头根节点\",\"label\":\"虚拟根节点\"}}],\"requestBody\":[{\"elementData\":{\"name\":\"root\",\"type\":\"OBJECT\",\"desc\":\"请求体根节点\",\"label\":\"虚拟根节点\"},\"children\":[{\"elementData\":{\"type\":\"STRING\",\"name\":\"opsEmpNumber\",\"required\":true,\"label\":\"%E6%93%8D%E4%BD%9C%E4%BA%BA%09\",\"exampleValue\":\"001\",\"desc\":\"%20%E5%A1%AB%E5%86%99%E5%91%98%E5%B7%A5%E8%8A%B1%E5%90%8D%E5%86%8C%E7%BC%96%E7%A0%81%0D%0A%0D%0A%0D%0A\"}},{\"elementData\":{\"type\":\"ARRAY\",\"name\":\"subjectTypes\",\"required\":false,\"label\":\"%E5%AF%BC%E5%85%A5%E9%A2%84%E7%AE%97%E7%A7%91%E7%9B%AE%E5%88%86%E7%B1%BB%E5%88%97%E8%A1%A8\",\"exampleValue\":\"\",\"desc\":\"%20%E4%BC%A0%E5%85%A5%E5%88%99%E8%BF%9B%E8%A1%8C%E5%AF%BC%E5%85%A5%E9%A2%84%E7%AE%97%E7%A7%91%E7%9B%AE%E5%88%86%E7%B1%BB%0A%E6%9C%80%E5%A4%9A%E6%94%AF%E6%8C%81%E4%BC%A0%E5%85%A5100%E6%9D%A1\",\"maxLength\":\"100\"},\"children\":[{\"elementData\":{\"type\":\"STRING\",\"name\":\"budgetSubTypeId\",\"required\":true,\"label\":\"%E9%A2%84%E7%AE%97%E7%A7%91%E7%9B%AE%E5%88%86%E7%B1%BBID\",\"exampleValue\":\"z001\",\"desc\":\"%20%E4%BB%85%E6%94%AF%E6%8C%81%E6%95%B0%E5%AD%97%E5%92%8C%E5%AD%97%E6%AF%8D\",\"maxLength\":\"50\"}},{\"elementData\":{\"type\":\"STRING\",\"name\":\"budgetSubTypeName\",\"required\":true,\"label\":\"%E9%A2%84%E7%AE%97%E7%A7%91%E7%9B%AE%E5%88%86%E7%B1%BB%E5%90%8D%E7%A7%B0\",\"exampleValue\":\"api%E5%AF%BC%E5%85%A5%E7%A7%91%E7%9B%AE%E5%88%86%E7%B1%BB\",\"desc\":\"%20%E9%A2%84%E7%AE%97%E7%A7%91%E7%9B%AE%E5%88%86%E7%B1%BB%E5%90%8D%E7%A7%B0\",\"maxLength\":\"150\"}}]},{\"elementData\":{\"type\":\"ARRAY\",\"name\":\"subjects\",\"required\":true,\"label\":\"%E5%AF%BC%E5%85%A5%E9%A2%84%E7%AE%97%E7%A7%91%E7%9B%AE%E5%88%97%E8%A1%A8\",\"exampleValue\":\"\",\"desc\":\"%20%E6%9C%80%E5%A4%9A%E6%94%AF%E6%8C%81%E4%BC%A0%E5%85%A5100%E6%9D%A1\",\"maxLength\":\"100\"},\"children\":[{\"elementData\":{\"type\":\"STRING\",\"name\":\"expIds\",\"required\":true,\"label\":\"%E9%A2%84%E7%AE%97%E7%A7%91%E7%9B%AE%E5%85%B3%E8%81%94%E8%B4%B9%E7%94%A8%E7%B1%BB%E5%9E%8Bid%E5%88%97%E8%A1%A8\",\"exampleValue\":\"01%2C02\",\"desc\":\"%20%E5%A1%AB%E5%86%99%E8%B4%B9%E7%94%A8%E7%B1%BB%E5%9E%8B%E7%BC%96%E7%A0%81%EF%BC%8C%E4%BB%A5%E8%8B%B1%E6%96%87%E9%80%97%E5%8F%B7%2C%E5%88%86%E5%89%B2\"}},{\"elementData\":{\"type\":\"STRING\",\"name\":\"subName\",\"required\":true,\"label\":\"%E9%A2%84%E7%AE%97%E7%A7%91%E7%9B%AE%E5%90%8D%E7%A7%B0\",\"exampleValue\":\"api%E6%B5%8B%E8%AF%95%E7%A7%91%E7%9B%AE%E5%90%8D%E7%A7%B01-1\",\"desc\":\"%20%E9%A2%84%E7%AE%97%E7%A7%91%E7%9B%AE%E5%90%8D%E7%A7%B0\",\"maxLength\":\"100\"}},{\"elementData\":{\"type\":\"STRING\",\"name\":\"subTypeId\",\"required\":true,\"label\":\"%E9%A2%84%E7%AE%97%E7%A7%91%E7%9B%AE%E6%89%80%E5%B1%9E%E5%88%86%E7%B1%BBID\",\"exampleValue\":\"z001\",\"desc\":\"%20%E4%BB%85%E6%94%AF%E6%8C%81%E6%95%B0%E5%AD%97%E5%92%8C%E5%AD%97%E6%AF%8D\",\"maxLength\":\"50\"}}]}]}],\"requestQuery\":[{\"elementData\":{\"name\":\"root\",\"type\":\"OBJECT\",\"desc\":\"query根节点\",\"label\":\"虚拟根节点\"}}]} <h2>接口输出参数</h2>{\"responseHeader\":[{\"elementData\":{\"name\":\"root\",\"type\":\"OBJECT\",\"desc\":\"响应头根节点\",\"label\":\"虚拟根节点\"}}],\"responseBody\":[{\"elementData\":{\"name\":\"root\",\"type\":\"OBJECT\",\"desc\":\"响应体根节点\",\"label\":\"虚拟根节点\"},\"children\":[{\"elementData\":{\"type\":\"OBJECT\",\"name\":\"data\",\"required\":false,\"label\":\"%E6%8E%A5%E5%8F%A3%E8%BF%94%E5%9B%9E%E5%AF%BC%E5%85%A5%E7%BB%93%E6%9E%9C%09\",\"exampleValue\":\"\",\"desc\":\"\"},\"children\":[{\"elementData\":{\"type\":\"BOOLEAN\",\"name\":\"success\",\"required\":false,\"label\":\"%E5%AF%BC%E5%85%A5%E6%98%AF%E5%90%A6%E6%88%90%E5%8A%9F%E7%8A%B6%E6%80%81%09\",\"exampleValue\":\"false\",\"desc\":\"%20true%E8%AF%B4%E6%98%8E%E5%AF%BC%E5%85%A5%E6%88%90%E5%8A%9F%0D%0Afalse%E8%AF%B4%E6%98%8E%E5%AF%BC%E5%85%A5%E5%A4%B1%E8%B4%A5\"}},{\"elementData\":{\"type\":\"ARRAY\",\"name\":\"errors\",\"required\":false,\"label\":\"%E5%AF%BC%E5%85%A5%E5%A4%B1%E8%B4%A5%E5%8E%9F%E5%9B%A0%E5%88%97%E8%A1%A8\",\"exampleValue\":\"\",\"desc\":\"%20%E5%A6%82%E6%9E%9C%E5%AF%BC%E5%85%A5%E5%A4%B1%E8%B4%A5%EF%BC%8C%E8%BF%99%E9%87%8C%E4%BC%9A%E8%BF%94%E5%9B%9E%E5%85%B7%E4%BD%93%E7%9A%84%E5%AF%BC%E5%85%A5%E5%A4%B1%E8%B4%A5%E5%8E%9F%E5%9B%A0%0D%0A%E5%A6%82%E6%9E%9C%E6%98%AF%E5%AF%BC%E5%85%A5%E6%88%90%E5%8A%9F%EF%BC%8C%E5%88%99%E4%B8%BA%E8%BF%99%E9%87%8C%E4%B8%BA%E7%A9%BA\"},\"children\":[{\"elementData\":{\"type\":\"STRING\",\"name\":\"type\",\"required\":false,\"label\":\"%E5%AF%BC%E5%85%A5%E5%A4%B1%E8%B4%A5%E7%9A%84%E5%8E%9F%E5%9B%A0%E7%B1%BB%E5%9E%8B\",\"exampleValue\":\"%E9%A2%84%E7%AE%97%E7%A7%91%E7%9B%AE%E5%88%86%E7%B1%BB%E7%BC%96%E7%A0%81\",\"desc\":\"%20%E9%A2%84%E7%AE%97%E7%A7%91%E7%9B%AE%E5%88%86%E7%B1%BB%E7%BC%96%E7%A0%81%0A%E9%A2%84%E7%AE%97%E7%A7%91%E7%9B%AE%E5%88%86%E7%B1%BB%E5%90%8D%E7%A7%B0%0A%E9%A2%84%E7%AE%97%E7%A7%91%E7%9B%AE%E5%90%8D%E7%A7%B0%0A%E5%85%81%E8%AE%B8%E5%8D%A0%E7%94%A8%E7%9A%84%E8%B4%B9%E7%94%A8%2F%E8%A1%A5%E8%B4%B4%E7%B1%BB%E5%9E%8B\"}},{\"elementData\":{\"type\":\"LONG\",\"name\":\"index\",\"required\":false,\"label\":\"%E5%AF%BC%E5%85%A5%E5%A4%B1%E8%B4%A5%E7%9A%84%E7%A7%91%E7%9B%AE%E5%BA%8F%E5%8F%B7\",\"exampleValue\":\"1\",\"desc\":\"\"}},{\"elementData\":{\"type\":\"ARRAY\",\"name\":\"msg\",\"required\":false,\"label\":\"%E5%AF%BC%E5%85%A5%E5%A4%B1%E8%B4%A5%E7%9A%84%E5%8E%9F%E5%9B%A0%E5%88%97%E8%A1%A8\",\"exampleValue\":\"%5B%22%E9%A2%84%E7%AE%97%E7%A7%91%E7%9B%AE%E5%88%86%E7%B1%BB%E5%90%8D%E7%A7%B0%E3%80%90api%E5%AF%BC%E5%85%A5%E7%A7%91%E7%9B%AE%E5%88%86%E7%B1%BB1%E3%80%91%E5%B7%B2%E5%AD%98%E5%9C%A8%22%2C%22%E9%A2%84%E7%AE%97%E7%A7%91%E7%9B%AE%E5%88%86%E7%B1%BB%E5%90%8D%E7%A7%B0%E3%80%90api%E5%AF%BC%E5%85%A5%E7%A7%91%E7%9B%AE%E5%88%86%E7%B1%BB1%E3%80%91%E6%9C%89%E9%87%8D%E5%A4%8D%E9%A1%B9%22%5D\",\"desc\":\"%20%E5%AF%BC%E5%85%A5%E5%A4%B1%E8%B4%A5%E5%8E%9F%E5%9B%A0%E5%88%97%E8%A1%A8%EF%BC%8C%E5%85%83%E7%B4%A0%E4%B8%BA%E5%85%B7%E4%BD%93%E5%A4%B1%E8%B4%A5%E5%8E%9F%E5%9B%A0%E5%AD%97%E7%AC%A6%E4%B8%B2\"},\"children\":[],\"open\":false}]}]},{\"elementData\":{\"type\":\"BOOLEAN\",\"name\":\"success\",\"required\":false,\"label\":\"%E6%8E%A5%E5%8F%A3%E8%B0%83%E7%94%A8%E6%88%90%E5%8A%9F%E7%8A%B6%E6%80%81%09\",\"exampleValue\":\"true\",\"desc\":\"%20true%E8%AF%B4%E6%98%8E%E6%8E%A5%E5%8F%A3%E8%B0%83%E7%94%A8%E6%88%90%E5%8A%9F%0D%0Afalse%E8%AF%B4%E6%98%8E%E6%8E%A5%E5%8F%A3%E8%B0%83%E7%94%A8%E5%A4%B1%E8%B4%A5\"}},{\"elementData\":{\"type\":\"STRING\",\"name\":\"message\",\"required\":false,\"label\":\"%E6%8E%A5%E5%8F%A3%E8%B0%83%E7%94%A8%E8%BF%94%E5%9B%9E%E4%BF%A1%E6%81%AF%09\",\"exampleValue\":\"%E8%B0%83%E7%94%A8%E6%88%90%E5%8A%9F%EF%BC%81\",\"desc\":\"\"}}]}]} <h2>接口调用示例</h2><h4>请求报文</h4>\n<pre><code class=\"language-json\">{\n  &quot;opsEmpNumber&quot;: &quot;2&quot;,\n  &quot;subjectTypes&quot;: [\n    {\n      &quot;budgetSubTypeId&quot;: &quot;z001&quot;,\n      &quot;budgetSubTypeName&quot;: &quot;api导入科目分类1&quot;\n    }\n  ],\n  &quot;subjects&quot;: [\n    {\n      &quot;expIds&quot;: &quot;01,02&quot;,\n      &quot;subName&quot;: &quot;api测试科目名称1-1&quot;,\n      &quot;subTypeId&quot;: &quot;z001&quot;\n    }\n  ]\n}\n</code></pre>\n<h4>响应报文</h4>\n<h4>接口调用失败的报文，示例仅为其中一部分失败样例</h4>\n<pre><code class=\"language-json\">{\n    &quot;success&quot;: false,\n    &quot;message&quot;: &quot;导入的预算科目分类和预算科目为空&quot;\n}\n</code></pre>\n<h4>导入成功的报文</h4>\n<pre><code class=\"language-json\">{\n    &quot;data&quot;: {\n        &quot;success&quot;: true,\n        &quot;errors&quot;: []\n    },\n    &quot;success&quot;: true,\n    &quot;message&quot;: &quot;调用成功！&quot;\n}\n</code></pre>\n<h4>导入失败的报文，示例仅为其中一部分失败样例</h4>\n<pre><code class=\"language-json\">{\n    &quot;data&quot;: {\n        &quot;success&quot;: false,\n        &quot;errors&quot;: [\n            {\n                &quot;type&quot;: &quot;预算科目分类编码&quot;,\n                &quot;index&quot;: 1,\n                &quot;msg&quot;: [\n                    &quot;预算科目分类编码【z001】已存在&quot;\n                ]\n            }\n        ]\n    },\n    &quot;success&quot;: true,\n    &quot;message&quot;: &quot;调用成功！&quot;\n}\n</code></pre>\n <h2>错误码说明</h2><p>外层success为接口调用状态 true为成功 其余都是失败\ndata内的sucess为实际导入成功状态， true为成功 其余都是失败</p>\n<p>常见报错如下：\n对于导入的预算科目分类列表：\n预算科目分类编码【xx】已存在\n预算科目分类编码【xx】有重复项\n预算科目分类名称【xx】已存在\n预算科目分类名称【xx】有重复项\n预算科目分类名称不能为空\n预算科目未配置费用或补助</p>\n<p>对于导入的预算科目列表：\n允许占用的费用/补贴类型【xx】不存在\n同一个科目不允许存在相同的费用/补贴类型\n预算科目名称【xx】已存在\n预算科目名称【xx】有重复项\n预算科目名称不能为空\n科目所属分类【xx】不存在</p>\n",
    "docCategory": "1",
    "docPublishRange": "2",
    "resourceId": null,
    "createUserId": null,
    "createUserName": null,
    "createTime": null,
    "updateUserId": null,
    "updateUserName": null,
    "updateTime": "2024-12-12 21:30:00",
    "docPublishTime": null,
    "menuOrder": null,
    "resourceName": null,
    "docClickCount": null,
    "docSource": null,
    "menuLevel": "10692-10689-14261",
    "menuLevelName": "开发文档/智能费控/预算",
    "highMenuName": null,
    "menuName": null,
    "fieldComponentOrNot": "Y",
    "highMenuId": 10692,
    "editorType": null
  }
}